akCore/__init__.py
akCore/sapi.py
akCore-0.0.1.dist-info/DESCRIPTION.rst
akCore-0.0.1.dist-info/METADATA
akCore-0.0.1.dist-info/RECORD
akCore-0.0.1.dist-info/WHEEL
akCore-0.0.1.dist-info/metadata.json
akCore-0.0.1.dist-info/top_level.txt
