Metadata-Version: 2.0
Name: akCore
Version: 0.0.1
Summary: Noob Pip
Home-page: UNKNOWN
Author: Alvin Bentus Karya
Author-email: alvinbentus@gmail.com
License: UNKNOWN
Platform: UNKNOWN
Classifier: Programming Language :: Python :: 2
Classifier: License :: OSI Approved :: MIT License
Classifier: Operating System :: OS Independent
